reflex_d3_graph/__init__.py
reflex_d3_graph/graph.py
reflex_d3_graph/types.py
reflex_d3_graph-0.0.1.dist-info/METADATA
reflex_d3_graph-0.0.1.dist-info/WHEEL
reflex_d3_graph-0.0.1.dist-info/top_level.txt
reflex_d3_graph-0.0.1.dist-info/RECORD
